Metadata-Version: 2.4
Name: sdiff
Version: 0.1.9
Summary: Rich file comparison with a focus on structured and tabular data
Author-email: Artem Pulkin <gpulkin@gmail.com>
License: BSD-2-Clause
Project-URL: Homepage, https://github.com/pulkin/sdiff
License-File: LICENSE.md
Requires-Dist: numpy
Requires-Dist: pandas
Requires-Dist: pyarrow
Requires-Dist: openpyxl
Requires-Dist: python-magic
Provides-Extra: dev
Requires-Dist: pytest; extra == "dev"
Requires-Dist: pytest-benchmark; extra == "dev"
Requires-Dist: sphinx; extra == "dev"
Requires-Dist: sphinx-rtd-theme; extra == "dev"
Dynamic: license-file
